CHANGELOG.txt
LICENSE
MANIFEST.in
README.md
requirements.txt
setup.py
lyrify/__init__.py
lyrify/lyrify.py
lyrify.egg-info/PKG-INFO
lyrify.egg-info/SOURCES.txt
lyrify.egg-info/dependency_links.txt
lyrify.egg-info/entry_points.txt
lyrify.egg-info/requires.txt
lyrify.egg-info/top_level.txt
lyrify/lyrics/__init__.py
lyrify/lyrics/genius.py
lyrify/music/__init__.py
lyrify/music/album.py
lyrify/music/music_tagger.py
lyrify/music/song.py
lyrify/utils/__init__.py
lyrify/utils/arguments.py
lyrify/utils/constants.py
lyrify/utils/errors.py
lyrify/utils/functions.py