Metadata-Version: 2.1
Name: lyrify
Version: 1.0.3
Summary: A simple CLI program to add lyrics to your mp3 files.
Home-page: UNKNOWN
Author: Benedikt Mielke
Author-email: xbenmmusicx@gmail.com
License: MIT
Keywords: music,tagger,tag,genius,lyrics,mp3,mutagen,song,sing
Platform: UNKNOWN
Classifier: Development Status :: 5 - Production/Stable
Classifier: Intended Audience :: End Users/Desktop
Classifier: Programming Language :: Python :: 3
Classifier: Operating System :: Microsoft :: Windows
Classifier: License :: OSI Approved :: MIT License
Classifier: Topic :: Multimedia :: Sound/Audio
